rorm/__init__.py
rorm/orm_cache.py
rorm/orm_model.py
tests/__init__.py
tests/test_cache.py
rorm_py-1.0.0.dist-info/LICENSE
rorm_py-1.0.0.dist-info/METADATA
rorm_py-1.0.0.dist-info/WHEEL
rorm_py-1.0.0.dist-info/top_level.txt
rorm_py-1.0.0.dist-info/RECORD
