Metadata-Version: 2.1
Name: rorm-py
Version: 1.0.0
Summary: A simple ORM cache library for redis
Home-page: https://github.com/huxiaohei/rorm-py
Author: 刘虎
Author-email: huxiaoheigame@gmail.com
License: MIT
Classifier: Programming Language :: Python :: 3
Classifier: License :: OSI Approved :: MIT License
Classifier: Operating System :: OS Independent
Requires-Python: >=3.9
License-File: LICENSE
Requires-Dist: annotated-types==0.7.0
Requires-Dist: pydantic==2.8.2
Requires-Dist: pydantic-core==2.20.1
Requires-Dist: redis==5.0.7
Requires-Dist: setuptools==75.1.0
Requires-Dist: typing-extensions==4.12.2
